{
    "0": {
        "Aliens Vs Predator Requiem.mp4\n": "Aliens Vs Predator Requiem.mp4"
    },
    "1": {
        "American Gangster (2007).mp4\n": "American Gangster (2007).mp4"
    },
    "2": {
        "American.Pie.1999.720p.x264.Br.YIFY-appletv.mp4\n": "American Pie 1999 Br.mp4"
    },
    "3": {
        "American.Pie.2.2001.720p.Br.x264.YIFY-appletv.mp4\n": "American Pie 2 2001 Br .mp4"
    },
    "4": {
        "American Pie 3 - The Wedding.YIFY-appletv.mp4\n": "American Pie 3 The Wedding.mp4"
    },
    "5": {
        "American.Pie.7-Presents.The.Book.of.Love.720p.x264.YIFY-appletv.mp4\n": "American Pie 7Presents The Book of Love .mp4"
    },
    "6": {
        "American.Pie.Band.Camp.720p.x264.YIFY-appletv.mp4\n": "American Pie Band Camp .mp4"
    },
    "7": {
        "American.Pie.Beta.House.720p.x264.YIFY-appletv.mp4\n": "American Pie Beta House .mp4"
    },
    "8": {
        "American.Pie.The.Naked.Mile.720p.YIFY-appletv.mp4\n": "American Pie The Naked Mile .mp4"
    },
    "9": {
        "American Virgin [2009]-appletv.mp4\n": "American Virgin [2009].mp4"
    },
    "10": {
        "An American werewolf in Paris KLAXXON-appletv.m4v\n": "An American werewolf in Paris KLAXXON.m4v"
    },
    "11": {
        "Anchorman[2004][Unrated]-appletv.mp4\n": "Anchorman[2004][Unrated].mp4"
    },
    "12": {
        "Anchorman[Unrated]DVDRip.Xvid.2004-tots-appletv.mp4\n": "Anchorman[Unrated] 2004tots.mp4"
    },
    "13": {
        "Angels and Demons[2009]-ps3.mp4\n": "Angels and Demons[2009].mp4"
    },
    "14": {
        "Anger Management-appletv.mp4\n": "Anger Management.mp4"
    },
    "15": {
        "Animated Movies\n": "Animated Movies"
    },
    "16": {
        "Anna.Karenina.2012.720p.BluRay.x264.YIFY-appletv.mp4\n": "Anna Karenina 2012 .mp4"
    },
    "17": {
        "Antwone Fisher-appletv.mp4\n": "Antwone Fisher.mp4"
    },
    "18": {
        "Any Given Sunday[1999]-appletv.mp4\n": "Any Given Sunday[1999].mp4"
    },
    "19": {
        "Argo.2012.720p.BluRay.x264.YIFY-appletv.mp4\n": "Argo 2012 .mp4"
    },
    "20": {
        "Armageddon[1998]DvDrip[Eng]-Zeus_Dias-appletv.mp4\n": "Armageddon[1998][Eng]Zeus_Dias.mp4"
    },
    "21": {
        "Armored[2010]DvDrip-LW-appletv.mp4\n": "Armored[2010]DvDripLW.mp4"
    },
    "22": {
        "Arthur ptI-appletv.m4v\n": "Arthur ptI.m4v"
    },
    "23": {
        "Arthur ptII-appletv.m4v\n": "Arthur ptII.m4v"
    },
    "24": {
        "Assassination of a High School President[2008]-appletv.mp4\n": "Assassination of a High School President[2008].mp4"
    },
    "25": {
        "Austin Powers In Goldmember-appletv.mp4\n": "Austin Powers In Goldmember.mp4"
    },
    "26": {
        "Austin Powers - The International Man Of Mystery-appletv.mp4\n": "Austin Powers The International Man Of Mystery.mp4"
    },
    "27": {
        "Austin Powers - The Spy Who Shagged Me-appletv.mp4\n": "Austin Powers The Spy Who Shagged Me.mp4"
    },
    "28": {
        "Awake (2007)-appletv.m4v\n": "Awake (2007).m4v"
    },
    "29": {
        "Back to the Future I-appletv.mp4\n": "Back to the Future I.mp4"
    },
    "30": {
        "Back to the Future II-appletv.mp4\n": "Back to the Future II.mp4"
    },
    "31": {
        "Back to the Future III-appletv.mp4\n": "Back to the Future III.mp4"
    },
    "32": {
        "Bangkok Dangerous[2008]-appletv.mp4\n": "Bangkok Dangerous[2008].mp4"
    },
    "33": {
        "Batman[1989]DvDrip-aXXo-appletv.mp4\n": "Batman[1989]DvDripaXXo.mp4"
    },
    "34": {
        "Batman.Begins[2005]DvDrip-aXXo-appletv.mp4\n": "Batman Begins[2005]DvDripaXXo.mp4"
    },
    "35": {
        "Batman.Forever[1995]DvDrip-aXXo-appletv.mp4\n": "Batman Forever[1995]DvDripaXXo.mp4"
    },
    "36": {
        "Batman.Returns[1992]DvDrip-aXXo-appletv.mp4\n": "Batman Returns[1992]DvDripaXXo.mp4"
    },
    "37": {
        "Batman.&.Robin[1997]DvDrip-aXXo-appletv.mp4\n": "Batman & Robin[1997]DvDripaXXo.mp4"
    },
    "38": {
        "Bebe's Kids-appletv.mp4\n": "Bebe's Kids.mp4"
    },
    "39": {
        "Because.I.Said.So[2007]DvDrip[Eng]-aXXo-appletv.mp4\n": "Because I Said So[2007][Eng].mp4"
    },
    "40": {
        "Beetlejuice-appletv.mp4\n": "Beetlejuice.mp4"
    },
    "41": {
        "Bewitched[2005]DvDrip[Eng]-aXXo-appletv3.mp4\n": "Bewitched[2005][Eng]aXXoappletv3.mp4"
    },
    "42": {
        "Biker boyz 2003 720p BluRay Dual Audio English Hindi GOPI SAHI PDR.mkv\n": "Biker boyz 2003 Dual Audio English Hindi GOPI SAHI PDR.mkv"
    },
    "43": {
        "Black Hawk Down [2001].mp4\n": "Black Hawk Down [2001].mp4"
    },
    "44": {
        "Black Knight-appletv.mp4\n": "Black Knight.mp4"
    },
    "45": {
        "Black Swan (2010)-appletv.mp4\n": "Black Swan (2010).mp4"
    },
    "46": {
        "Blade 2[2002]DvDrip[Eng]-BugZ-appletv.mp4\n": "Blade 2[2002][Eng]BugZ.mp4"
    },
    "47": {
        "Blade-DvDrip-RWD-3-appletv.mp4\n": "BladeDvDripRWD3.mp4"
    },
    "48": {
        "Blade I-appletv.mp4\n": "Blade I.mp4"
    },
    "49": {
        "Blades.Of.Glory[2007]DvDrip.AC3[Eng]-aXXo-appletv.mp4\n": "Blades Of Glory[2007] [Eng].mp4"
    },
    "50": {
        "Blankman[1994]XviD-eXtasy-appletv.mp4\n": "Blankman[1994]XviDeXtasy.mp4"
    },
    "51": {
        "Blood And Bone.2009.DvdRip.Xvid {1337x}-Noir-appletv.mp4\n": "Blood And Bone 2009 {}Noir.mp4"
    },
    "52": {
        "Blood The Last Vampire.mp4\n": "Blood The Last Vampire.mp4"
    },
    "53": {
        "Blow[2001]-appletv.mp4\n": "Blow[2001].mp4"
    },
    "54": {
        "Body Of Lies[2008]-appletv.mp4\n": "Body Of Lies[2008].mp4"
    },
    "55": {
        "Boomerang [1992][DVDrip][eng] - By.Smelly-Cat-appletv.mp4\n": "Boomerang [1992][][eng] By SmellyCat.mp4"
    },
    "56": {
        "Booty.Call.1997.WS.XVID.DVDRIP-appletv.mp4\n": "Booty Call 1997 WS .mp4"
    },
    "57": {
        "BOYZ IN THA HOOD-appletv.mp4\n": "BOYZ IN THA HOOD.mp4"
    },
    "58": {
        "Braveheart.1995.1080p.BrRip.x264.YIFY+HI.mp4\n": "Braveheart 1995 +HI.mp4"
    },
    "59": {
        "breakin2-ps3-appletv.mp4\n": "breakin2ps3.mp4"
    },
    "60": {
        "Breakin.All.the.Rules[2004]DvDrip[Eng]-codeblack-appletv.mp4\n": "Breakin All the Rules[2004][Eng]codeblack.mp4"
    },
    "61": {
        "Bride of Chucky[h33t][mattlb0619][H264-AAC][DVDRip]-appletv.mp4\n": "Bride of Chucky[h33t][mattlb0619][H264][].mp4"
    },
    "62": {
        "Bridesmaids 2011 TS XViD DTRG-appletv.mp4\n": "Bridesmaids 2011 TS DTRG.mp4"
    },
    "63": {
        "Bridge of Spies 2015 1080p BluRay x264 DTS-JYK.mkv\n": "Bridge of Spies 2015 .mkv"
    },
    "64": {
        "Brokeback.Mountain.2005.1080p.Bluray.x264.anoXmous-ps3.mp4\n": "Brokeback Mountain 2005 anoXmousps3.mp4"
    },
    "65": {
        "Broken.City.2013.720p.BRrip.x264.GAZ.YIFY-appletv.mp4\n": "Broken City 2013 GAZ.mp4"
    },
    "66": {
        "Brothers [2009]-ps3-appletv.mp4\n": "Brothers [2009].mp4"
    },
    "67": {
        "Burn After Reading[2008]-ps3-appletv.mp4\n": "Burn After Reading[2008].mp4"
    },
    "68": {
        "Captain.America.Civil.War.2016.720p.BrRip.2CH.x265.HEVC-PSA.mkv\n": "Captain America Civil War 2016 2CH x265 HEVCPSA.mkv"
    },
    "69": {
        "Captain.America.The.Winter.Soldier.2014.1080p.BluRay.x264.YIFY.mp4\n": "Captain America The Winter Soldier 2014 .mp4"
    },
    "70": {
        "Captain Phillips (2013) DVDRip XviD-MAXSPEED www.torentz.3xforum.ro-ps3.mp4\n": "Captain Phillips (2013) XviDMAXSPEED www torentz 3xforum rops3.mp4"
    },
    "71": {
        "Captain Ron-appletv.mp4\n": "Captain Ron.mp4"
    },
    "72": {
        "Cars.2006.720p.Funsaber.mkv\n": "Cars 2006 Funsaber.mkv"
    },
    "73": {
        "Cars.2.2011.720p.Funsaber.mkv\n": "Cars 2 2011 Funsaber.mkv"
    },
    "74": {
        "Cars.3.2017.720p.BluRay.x264.MkvCage-[my-Film].mkv\n": "Cars 3 2017 MkvCage[myFilm].mkv"
    },
    "75": {
        "Case 39 [2009]-ps3-appletv.mp4\n": "Case 39 [2009].mp4"
    },
    "76": {
        "Casino Royale 2006 HD 720p-appletv.mp4\n": "Casino Royale 2006 HD.mp4"
    },
    "77": {
        "Cast Away pt1(2000)-ps3-appletv.mp4\n": "Cast Away pt1(2000).mp4"
    },
    "78": {
        "Cast Away pt2 (2000)-ps3-appletv.mp4\n": "Cast Away pt2 (2000).mp4"
    },
    "79": {
        "Catch Me If You Can-ps3-appletv.mp4\n": "Catch Me If You Canps3.mp4"
    },
    "80": {
        "Changeling[2008]-ps3-appletv.mp4\n": "Changeling[2008].mp4"
    },
    "81": {
        "Chaos Theory (2008)-ps3-appletv.mp4\n": "Chaos Theory (2008).mp4"
    },
    "82": {
        "Charlie Bartlett (2007)-ps3-appletv.mp4\n": "Charlie Bartlett (2007).mp4"
    },
    "83": {
        "Children.of.the.Corn.Genesis.2011.DVDRip.Xvid.AC3-SiC-appletv.mp4\n": "Children of the Corn Genesis 2011 AC3SiC.mp4"
    },
    "84": {
        "Childs Play 2[h33t][mattlb0619][H264-AAC][DVDRip]-appletv.mp4\n": "Childs Play 2[h33t][mattlb0619][H264][].mp4"
    },
    "85": {
        "Childs Play 3[h33t][mattlb0619][H264-AAC][DVDRip]-appletv.mp4\n": "Childs Play 3[h33t][mattlb0619][H264][].mp4"
    },
    "86": {
        "Childs Play[h33t][mattlb0619][H264-AAC][DVDRip]-appletv.mp4\n": "Childs Play[h33t][mattlb0619][H264][].mp4"
    },
    "87": {
        "Choke[2008]DvDrip[Eng]-FXG-appletv.mp4\n": "Choke[2008][Eng]FXG.mp4"
    },
    "88": {
        "Chronicle.2012.1080p.BrRip.x264.YIFY.mp4\n": "Chronicle 2012 .mp4"
    },
    "89": {
        "Collateral-ps3-appletv.mp4\n": "Collateralps3.mp4"
    },
    "90": {
        "College (2008)-appletv.mp4\n": "College (2008).mp4"
    },
    "91": {
        "College Road Trip (2008)-appletv.mp4\n": "College Road Trip (2008).mp4"
    },
    "92": {
        "Colombiana.2011-ps3-appletv.mp4\n": "Colombiana 2011ps3.mp4"
    },
    "93": {
        "Coming to America.[1988].DVDRIP.XVID.[Eng]-DUQA-appletv.mp4\n": "Coming to America [1988] [Eng]DUQA.mp4"
    },
    "94": {
        "Couples Retreat {2009} DVDRIP Jaybob-appletv.mp4\n": "Couples Retreat {2009} Jaybob.mp4"
    },
    "95": {
        "Crash[2005]-ps3-appletv.mp4\n": "Crash[2005].mp4"
    },
    "96": {
        "Crazy, Stupid Love A-ps3-appletv.mp4\n": "Crazy, Stupid Love Aps3.mp4"
    },
    "97": {
        "Crazy, Stupid Love B-ps3-appletv.mp4\n": "Crazy, Stupid Love Bps3.mp4"
    },
    "98": {
        "Creed.2015.720p.BRRip.x264.AAC-ETRG.mp4\n": "Creed 2015 ETRG.mp4"
    },
    "99": {
        "Cruel Intentions[1999]DvDrip[Eng]-Stealthmaster-appletv.mp4\n": "Cruel Intentions[1999][Eng]Stealthmaster.mp4"
    },
    "100": {
        "Cruel Intentions 2.LKRG-appletv.mp4\n": "Cruel Intentions 2 LKRG.mp4"
    },
    "101": {
        "Cruel Intentions 3.LKRG-appletv.mp4\n": "Cruel Intentions 3 LKRG.mp4"
    },
    "102": {
        "Dance Flick.2009.DvdRip.Xvid {1337x}-Noir-appletv.mp4\n": "Dance Flick 2009 {}Noir.mp4"
    },
    "103": {
        "Dan in Real Life (2007)-appletv.mp4\n": "Dan in Real Life (2007).mp4"
    },
    "104": {
        "Darkness Falls 2003-ps3-appletv.mp4\n": "Darkness Falls 2003ps3.mp4"
    },
    "105": {
        "Daybreakers-ps3-appletv.mp4\n": "Daybreakersps3.mp4"
    },
    "106": {
        "Day Of The Dead - (1985) - George A Romero-appletv.mp4\n": "Day Of The Dead (1985) George A Romero.mp4"
    },
    "107": {
        "Day.Of.The.Dead.2008.Eng.DVDRip.DivX-LTT-appletv.mp4\n": "Day Of The Dead 2008 Eng DivXLTT.mp4"
    },
    "108": {
        "Dead.Like.Me-Life.After.Death[2009]DvDrip-aXXo-appletv.mp4\n": "Dead Like MeLife After Death[2009]DvDripaXXo.mp4"
    },
    "109": {
        "Dead Silence-ETRG-ps3-appletv.mp4\n": "Dead SilenceETRGps3.mp4"
    },
    "110": {
        "Death At A Funeral[2010]-ps3-appletv.mp4\n": "Death At A Funeral[2010].mp4"
    },
    "111": {
        "Death Race (2008)-ps3-appletv.mp4\n": "Death Race (2008).mp4"
    },
    "112": {
        "Death Race 2 [2010]-ps3-appletv.mp4\n": "Death Race 2 [2010].mp4"
    },
    "113": {
        "Death.Race.3.2013.UNRATED.1080p.Bluray.x264-ps3-appletv.mp4\n": "Death Race 3 2013 UNRATED x264ps3.mp4"
    },
    "114": {
        "Deception (2008)-ps3-appletv.mp4\n": "Deception (2008).mp4"
    },
    "115": {
        "deck.the.halls.2006.720p.bluray.x264-psychd-appletv3.mp4\n": "deck the halls 2006 x264psychdappletv3.mp4"
    },
    "116": {
        "Deliver Us From Eva 2003 DvDrip[Eng]-greenbud1969-appletv.mp4\n": "Deliver Us From Eva 2003 [Eng]greenbud1969.mp4"
    },
    "117": {
        "Dennis The Menace-appletv3.mp4\n": "Dennis The Menaceappletv3.mp4"
    },
    "118": {
        "Deuce Bigalow Male Gigolo KLAXXON-ps3-appletv.mp4\n": "Deuce Bigalow Male Gigolo KLAXXONps3.mp4"
    },
    "119": {
        "devise-hangoverts-appletv.mp4\n": "devisehangoverts.mp4"
    },
    "120": {
        "devise-rounders.cd1-ps3-appletv.mp4\n": "deviserounders cd1ps3.mp4"
    },
    "121": {
        "devise-rounders.cd2-ps3-appletv.mp4\n": "deviserounders cd2ps3.mp4"
    },
    "122": {
        "Diary of the Dead-appletv.mp4\n": "Diary of the Dead.mp4"
    },
    "123": {
        "Die Hard 4 - Live Free or Die Hard-ps3-appletv.mp4\n": "Die Hard 4 Live Free or Die Hardps3.mp4"
    },
    "124": {
        "Django Unchained DVD Screener-ps3-ps3-appletv.mp4\n": "Django Unchained DVD Screenerps3ps3.mp4"
    },
    "125": {
        "dmd-sfchunli-ps3-appletv.mp4\n": "dmdsfchunlips3.mp4"
    },
    "126": {
        "dmd-up-ps3-appletv.mp4\n": "dmdupps3.mp4"
    },
    "127": {
        "Dodgeball-ps3-appletv.mp4\n": "Dodgeballps3.mp4"
    },
    "128": {
        "dont be a menace to south central[DVDRIP]XVID,AC3(KNIGHTY1973)1986-appletv.mp4\n": "dont be a menace to south central[],(KNIGHTY1973)1986.mp4"
    },
    "129": {
        "DoomsDay(2008)-ps3-appletv.mp4\n": "DoomsDay(2008).mp4"
    },
    "130": {
        "Eagle Eye[2008]-ps3-appletv.mp4\n": "Eagle Eye[2008].mp4"
    },
    "131": {
        "easy.a.2010.bdrip.xvid-imbt-ps3-appletv.mp4\n": "easy a 2010 xvidimbtps3.mp4"
    },
    "132": {
        "Edward Scissorhands[1990]-ps3-appletv.mp4\n": "Edward Scissorhands[1990].mp4"
    },
    "133": {
        "Elephants_Dream_HD-ps3-appletv.mp4\n": "Elephants_Dream_HDps3.mp4"
    },
    "134": {
        "Elysium.2013.1080p.BluRay.x264.YIFY-appletv3.mp4\n": "Elysium 2013 appletv3.mp4"
    },
    "135": {
        "End.of.Watch.2012.720p.BluRay.x264.YIFY-ps3-appletv.mp4\n": "End of Watch 2012 .mp4"
    },
    "136": {
        "Eurotrip.2004.Unrated.DivX5.AC3.CD1-WAF-appletv.mp4\n": "Eurotrip 2004 Unrated DivX5 CD1WAF.mp4"
    },
    "137": {
        "Eurotrip.2004.Unrated.DivX5.AC3.CD2-WAF-appletv.mp4\n": "Eurotrip 2004 Unrated DivX5 CD2WAF.mp4"
    },
    "138": {
        "Face Off-ps3-appletv.mp4\n": "Face Offps3.mp4"
    },
    "139": {
        "Fahrenheit 911 [2004]CD1-appletv.mp4\n": "Fahrenheit 911 [2004]CD1.mp4"
    },
    "140": {
        "Fahrenheit 911 [2004]CD2-appletv.mp4\n": "Fahrenheit 911 [2004]CD2.mp4"
    },
    "141": {
        "Failure.To.Launch[2006]DvDrip.AC3[Eng]-aXXo-ps3-appletv.mp4\n": "Failure To Launch[2006] [Eng]aXXops3.mp4"
    },
    "142": {
        "Fast and Furious 5 Fast Five (2011) DVDRip XviD-MAXSPEED www.torentz.3xforum.ro-ps3-appletv.mp4\n": "Fast and Furious 5 Fast Five (2011) XviDMAXSPEED www torentz 3xforum rops3.mp4"
    },
    "143": {
        "Faster[2010]-ps3-appletv.mp4\n": "Faster[2010].mp4"
    },
    "144": {
        "Fast & Furious 4 [2009]-appletv.mp4\n": "Fast & Furious 4 [2009].mp4"
    },
    "145": {
        "Fast & Furious Tokyo Drift-appletv.mp4\n": "Fast & Furious Tokyo Drift.mp4"
    },
    "146": {
        "Fatal Needles VS Fatal Fists [1978]-ps3-appletv.mp4\n": "Fatal Needles VS Fatal Fists [1978].mp4"
    },
    "147": {
        "Felon (2008)-ps3-appletv.mp4\n": "Felon (2008).mp4"
    },
    "148": {
        "Fighting [2009]-ps3-appletv.mp4\n": "Fighting [2009].mp4"
    },
    "149": {
        "Final.Destination[2000]DvDrip-aXXo-ps3-appletv.mp4\n": "Final Destination[2000]DvDripaXXops3.mp4"
    },
    "150": {
        "Final.Destination.2[2003]DvDrip-aXXo-ps3-appletv.mp4\n": "Final Destination 2[2003]DvDripaXXops3.mp4"
    },
    "151": {
        "Final.Destination.3[2006]DvDrip-aXXo-ps3-appletv.mp4\n": "Final Destination 3[2006]DvDripaXXops3.mp4"
    },
    "152": {
        "Fired.Up.2009.UNRATED.DVDRiP.XViD-ARROW-appletv.mp4\n": "Fired Up 2009 UNRATED XViDARROW.mp4"
    },
    "153": {
        "Fireproof [2008]DVDRip[Xvid]AC3 5.1[Eng]BlueLady-appletv3.mp4\n": "Fireproof [2008][] 5 1[Eng]BlueLadyappletv3.mp4"
    },
    "154": {
        "flashdance.1983.720p.HDTV.solstars-ps3-appletv.mp4\n": "flashdance 1983 HDTV solstarsps3.mp4"
    },
    "155": {
        "Flight.2012.720p.BrRipx264.YIFY-appletv.mp4\n": "Flight 2012 BrRipx264.mp4"
    },
    "156": {
        "Flight.2012.720p.BrRipx264.YIFY-ps3-appletv.mp4\n": "Flight 2012 BrRipx264.mp4"
    },
    "157": {
        "Fool's Gold (2008)-appletv.mp4\n": "Fool's Gold (2008).mp4"
    },
    "158": {
        "Forest Gump [1994] DVDRip - N!CK-ps3-appletv.mp4\n": "Forest Gump [1994] N!CKps3.mp4"
    },
    "159": {
        "Forgetting Sarah Marshall (2008)-appletv.mp4\n": "Forgetting Sarah Marshall (2008).mp4"
    },
    "160": {
        "Freedom.Writers[2007]DvDrip[Eng]-aXXo-ps3-appletv.mp4\n": "Freedom Writers[2007][Eng]aXXops3.mp4"
    },
    "161": {
        "Friday After Next-ps3-appletv.mp4\n": "Friday After Nextps3.mp4"
    },
    "162": {
        "friday-pfa-ps3-appletv.mp4\n": "fridaypfaps3.mp4"
    },
    "163": {
        "Frozen 2013 DVDScr XViD AC3-FiNGERBLaST-ps3.mp4\n": "Frozen 2013 DVDScr AC3FiNGERBLaSTps3.mp4"
    },
    "164": {
        "Funny People (2009) DVDRip XviD-MAXSPEED www.torentz.3xforum.ro-appletv.mp4\n": "Funny People (2009) XviDMAXSPEED www torentz 3xforum ro.mp4"
    },
    "165": {
        "FURIOUS_6_BLUEBIRD-appletv.mp4\n": "FURIOUS_6_BLUEBIRD.mp4"
    },
    "166": {
        "Gamer.2009.DvdRip.Xvid {1337x}-Noir-appletv.mp4\n": "Gamer 2009 {}Noir.mp4"
    },
    "167": {
        "Gangs Of New York 2-ps3-appletv.mp4\n": "Gangs Of New York 2ps3.mp4"
    },
    "168": {
        "Gangs Of New York-ps3-appletv.mp4\n": "Gangs Of New Yorkps3.mp4"
    },
    "169": {
        "Get Him to the Greek (2010) DVDRip XviD-MAXSPEED www.torentz.3xforum.ro-ps3-appletv.mp4\n": "Get Him to the Greek (2010) XviDMAXSPEED www torentz 3xforum rops3.mp4"
    },
    "170": {
        "Get Smart-ps3-appletv.mp4\n": "Get Smartps3.mp4"
    },
    "171": {
        "Ghosts of Girlfriends Past [2009]-appletv.mp4\n": "Ghosts of Girlfriends Past [2009].mp4"
    },
    "172": {
        "Ghost.Town[2008]-appletv.mp4\n": "Ghost Town[2008].mp4"
    },
    "173": {
        "G.I. Jane (1997) 720p BrRip x264 YIFY-appletv.mp4\n": "G I Jane (1997) .mp4"
    },
    "174": {
        "G.I. Joe-The Rise Of Cobra[2009]-ps3-appletv.mp4\n": "G I JoeThe Rise Of Cobra[2009].mp4"
    },
    "175": {
        "Girl, Interrupted 1999 DvDrip[Eng]-greenbud1969-ps3-appletv.mp4\n": "Girl, Interrupted 1999 [Eng]greenbud1969ps3.mp4"
    },
    "176": {
        "Godfather part III-ps3-appletv.mp4\n": "Godfather part IIIps3.mp4"
    },
    "177": {
        "Godfather part II-ps3-appletv.mp4\n": "Godfather part IIps3.mp4"
    },
    "178": {
        "God father part I-ps3-appletv.mp4\n": "God father part Ips3.mp4"
    },
    "179": {
        "Godzilla.2014.1080p.BluRay.x264.YIFY.mp4\n": "Godzilla 2014 .mp4"
    },
    "180": {
        "Good.Burger.DVDRip.ethan420-ps3-appletv.mp4\n": "Good Burger ethan420ps3.mp4"
    },
    "181": {
        "Gran.Torino.2008.DvDRip-FxM-ps3-appletv.mp4\n": "Gran Torino 2008 DvDRipFxMps3.mp4"
    },
    "182": {
        "Grease (1978) DivX 720p (moviesbyrizzo)-appletv.mp4\n": "Grease (1978) DivX (moviesbyrizzo).mp4"
    },
    "183": {
        "Green Zone-appletv.mp4\n": "Green Zone.mp4"
    },
    "184": {
        "Guess.Who.2005.720p.BrRip.x264.YIFY-appletv3.mp4\n": "Guess Who 2005 appletv3.mp4"
    },
    "185": {
        "Gulliver's Travels-appletv.mp4\n": "Gulliver's Travels.mp4"
    },
    "186": {
        "Half Baked[1998]DvDrip[Eng]-Grimmo-appletv.mp4\n": "Half Baked[1998][Eng]Grimmo.mp4"
    },
    "187": {
        "Hall Pass (2011) DVDRip XviD-MAXSPEED www.torentz.3xforum.ro-appletv.mp4\n": "Hall Pass (2011) XviDMAXSPEED www torentz 3xforum ro.mp4"
    },
    "188": {
        "Hancock (2008)-appletv.mp4\n": "Hancock (2008).mp4"
    },
    "189": {
        "Hansel.and.Gretel.2013.1080p.BluRay.x264.YIFY-appletv.mp4\n": "Hansel and Gretel 2013 .mp4"
    },
    "190": {
        "Hardball[2001]-appletv.mp4\n": "Hardball[2001].mp4"
    },
    "191": {
        "Harold and Kumar Escape From Guanta Bay(2008)-appletv.mp4\n": "Harold and Kumar Escape From Guanta Bay(2008).mp4"
    },
    "192": {
        "Harry.Potter.and.the.Chamber.of.Secrets.2002.1080p.BrRip.x264.YIFY-appletv3.mp4\n": "Harry Potter and the Chamber of Secrets 2002 appletv3.mp4"
    },
    "193": {
        "Harry Potter and the Deathly Hallows Part 1 (2010) 1080p.BRrip.scOrp.sujaidr (pimprg)-appletv3.m4v\n": "Harry Potter and the Deathly Hallows Part 1 (2010) scOrp sujaidr (pimprg)appletv3.m4v"
    },
    "194": {
        "Harry Potter and the Deathly Hallows - Part 2 (2011)-appletv3.m4v\n": "Harry Potter and the Deathly Hallows Part 2 (2011)appletv3.m4v"
    },
    "195": {
        "Harry.Potter.and.the.Goblet.of.Fire.2005.1080p.BrRip.x264.YIFY-appletv3.mp4\n": "Harry Potter and the Goblet of Fire 2005 appletv3.mp4"
    },
    "196": {
        "Harry.Potter.and.the.Half.Blood.Prince.2009.1080p.BrRip.x264.YIFY-appletv3.mp4\n": "Harry Potter and the Half Blood Prince 2009 appletv3.mp4"
    },
    "197": {
        "Harry.Potter.and.the.Order.of.the.Phoenix.2007.1080p.BrRip.x264.YIFY-appletv3.mp4\n": "Harry Potter and the Order of the Phoenix 2007 appletv3.mp4"
    },
    "198": {
        "Harry.Potter.and.the.Prisoner.of.Azkaban.2004.1080p.BrRip.x264.YIFY-appletv3.mp4\n": "Harry Potter and the Prisoner of Azkaban 2004 appletv3.mp4"
    },
    "199": {
        "Harry.Potter.and.the.Sorcerers.Stone.2001.1080p.BrRip.x264.YIFY ( FIRST TRY)-appletv3.mp4\n": "Harry Potter and the Sorcerers Stone 2001 ( FIRST TRY)appletv3.mp4"
    },
    "200": {
        "Hellboy 2 The Golden Army(2008)-appletv.mp4\n": "Hellboy 2 The Golden Army(2008).mp4"
    },
    "201": {
        "Here.Comes.the.Boom.2012.720p.BluRay.x264.YIFY-appletv.mp4\n": "Here Comes the Boom 2012 .mp4"
    },
    "202": {
        "He's Just Not That Into You[2009]DvDrip[Eng]-FXG-appletv.mp4\n": "He's Just Not That Into You[2009][Eng]FXG.mp4"
    },
    "203": {
        "Hitman(2007)-appletv.mp4\n": "Hitman(2007).mp4"
    },
    "204": {
        "Hole.In.One.2010.DVDRipx264.YIFY-appletv.mp4\n": "Hole In One 2010 DVDRipx264.mp4"
    },
    "205": {
        "Home Alone 2 [DVDRip][Eng][1992]-appletv.mp4\n": "Home Alone 2 [][Eng][1992].mp4"
    },
    "206": {
        "Home Alone 3[DVDRip][1997][Eng]-appletv.mp4\n": "Home Alone 3[][1997][Eng].mp4"
    },
    "207": {
        "Home Alone 4 [DVDRip][2002][Eng]-appletv.mp4\n": "Home Alone 4 [][2002][Eng].mp4"
    },
    "208": {
        "Home Alone [DVDRip][Eng][1990]-appletv.mp4\n": "Home Alone [][Eng][1990].mp4"
    },
    "209": {
        "Horton Hears a Who (2008)-appletv.mp4\n": "Horton Hears a Who (2008).mp4"
    },
    "210": {
        "Hostel 1 2005 Jay Hernandez horror mystery thriller-appletv.mp4\n": "Hostel 1 2005 Jay Hernandez horror mystery thriller.mp4"
    },
    "211": {
        "Hostel 2 2007 Lauren German horror thriller-appletv.mp4\n": "Hostel 2 2007 Lauren German horror thriller.mp4"
    },
    "212": {
        "Hotel.Transylvania.2012.720p.BluRay.x264.YIFY-appletv.mp4\n": "Hotel Transylvania 2012 .mp4"
    },
    "213": {
        "HOUSE ON HAUNTED HILL [1999-Eng-DVDrip]-haSak-appletv.mp4\n": "HOUSE ON HAUNTED HILL [1999EngDVDrip]haSak.mp4"
    },
    "214": {
        "How.Do.You.Know.2010.DVDRip.Original-appletv.mp4\n": "How Do You Know 2010 Original.mp4"
    },
    "215": {
        "How High.DvDrip.Xvid + NL SUBS-appletv.mp4\n": "How High + NL SUBS.mp4"
    },
    "216": {
        "How.To.Be.A.Player.(1997).Dvdrip.Divx-Sfcr.Svcdplaza-appletv.mp4\n": "How To Be A Player (1997) DivxSfcr Svcdplaza.mp4"
    },
    "217": {
        "How.To.Lose.A.Guy.In.10.Days.2003.720p.BrRip.x264.YIFY-appletv3.mp4\n": "How To Lose A Guy In 10 Days 2003 appletv3.mp4"
    },
    "218": {
        "How To Lose Friends and Alienate People[2008]-appletv.mp4\n": "How To Lose Friends and Alienate People[2008].mp4"
    },
    "219": {
        "How to Train Your Dragon-appletv.mp4\n": "How to Train Your Dragon.mp4"
    },
    "220": {
        "I Am Legend (2007)-appletv.mp4\n": "I Am Legend (2007).mp4"
    },
    "221": {
        "Identity.Thief.2013.720p.BluRay.x264.YIFY-appletv.mp4\n": "Identity Thief 2013 .mp4"
    },
    "222": {
        "I Love You Beth Cooper [2009]-appletv.mp4\n": "I Love You Beth Cooper [2009].mp4"
    },
    "223": {
        "I Love You Man [2009]-appletv.mp4\n": "I Love You Man [2009].mp4"
    },
    "224": {
        "I Love You Phillip Morris-appletv.mp4\n": "I Love You Phillip Morris.mp4"
    },
    "225": {
        "Imperium.2016.720p.WEBRip.x264.AAC-ETRG.mp4\n": "Imperium 2016 WEBRip ETRG.mp4"
    },
    "226": {
        "Insurgent.2015.720p.BluRay.x264.YIFY.mp4\n": "Insurgent 2015 .mp4"
    },
    "227": {
        "Interview with the Vampire The Vampire Chronicles (1994).mp4\n": "Interview with the Vampire The Vampire Chronicles (1994).mp4"
    },
    "228": {
        "IP.Man.2008.BRRip.XviD.AC3-ViSiON-appletv.mp4\n": "IP Man 2008 AC3ViSiON.mp4"
    },
    "229": {
        "IP.MAN.The.Legend.is.Born.2010.DVDRip.BBa-appletv.mp4\n": "IP MAN The Legend is Born 2010 BBa.mp4"
    },
    "230": {
        "Iron.Man.2.2010.1080p.BrRip.x264.YIFY.mp4\n": "Iron Man 2 2010 .mp4"
    },
    "231": {
        "Iron.Man.3.2013.1080p.BluRay.x264.YIFY-appletv3.mp4\n": "Iron Man 3 2013 appletv3.mp4"
    },
    "232": {
        "Iron.Man.3.2013.720p.BluRay.x264.YIFY.mp4\n": "Iron Man 3 2013 .mp4"
    },
    "233": {
        "I Spit on Your Grave[2010][Unrated Edition]DvDrip[Eng]-FXG-appletv.mp4\n": "I Spit on Your Grave[2010][Unrated Edition][Eng]FXG.mp4"
    },
    "234": {
        "It's Complicated.mp4\n": "It's Complicated.mp4"
    },
    "235": {
        "Jackass 3D-appletv.mp4\n": "Jackass 3D.mp4"
    },
    "236": {
        "Jackass.Presents.Bad.Grandpa.2013.720p.BluRay.x264.YIFY-ps3.mp4\n": "Jackass Presents Bad Grandpa 2013 .mp4"
    },
    "237": {
        "Jack.Reacher.2012.720p.BRrip.x264.GAZ.YIFY-appletv.mp4\n": "Jack Reacher 2012 GAZ.mp4"
    },
    "238": {
        "James.Bond.Quantum.of.Solace.2008.1080p.BRrip.x264.YIFY-appletv.mp4\n": "James Bond Quantum of Solace 2008 .mp4"
    },
    "239": {
        "Jarhead.2005.1080p.BrRip.x264.YIFY-appletv.mp4\n": "Jarhead 2005 .mp4"
    },
    "240": {
        "Jason.Bourne.2016.HC.720p.HDRiP.x264.ShAaNiG.mkv\n": "Jason Bourne 2016 HC HDRiP ShAaNiG.mkv"
    },
    "241": {
        "jennifers.body.dvdrip.xvid-imbt-appletv.mp4\n": "jennifers body xvidimbt.mp4"
    },
    "242": {
        "Jet Li - Fist Of Legend [ENG DUB](DivX)jjj-appletv.mp4\n": "Jet Li Fist Of Legend [ENG DUB](DivX)jjj.mp4"
    },
    "243": {
        "JET LI HERO - ENG SUB AVI HQ-appletv.mp4\n": "JET LI HERO ENG SUB AVI HQ.mp4"
    },
    "244": {
        "Jingle.All.The.Way.1996.EXTENDED.720p.BrRip.x264.YIFY-appletv3.mp4\n": "Jingle All The Way 1996 EXTENDED appletv3.mp4"
    },
    "245": {
        "Joe Dirt-appletv.mp4\n": "Joe Dirt.mp4"
    },
    "246": {
        "Jumper(2008)-appletv.mp4\n": "Jumper(2008).mp4"
    },
    "247": {
        "Juno-appletv.mp4\n": "Juno.mp4"
    },
    "248": {
        "Jurassic.Park[1993]DvDrip-aXXo-appletv.mp4\n": "Jurassic Park[1993]DvDripaXXo.mp4"
    },
    "249": {
        "Just Go With It-appletv.mp4\n": "Just Go With It.mp4"
    },
    "250": {
        "Just Married [2003] [DVDRip XviD] [1337x]-Dita496-appletv.mp4\n": "Just Married [2003] [ ] []Dita496.mp4"
    },
    "251": {
        "Kangaroo Jack-appletv.mp4\n": "Kangaroo Jack.mp4"
    },
    "252": {
        "killbill1.divx.vice-appletv.mp4\n": "killbill1 divx vice.mp4"
    },
    "253": {
        "killbill2.divx.vice-appletv.mp4\n": "killbill2 divx vice.mp4"
    },
    "254": {
        "Killing.Season.2013.720p.BluRay.x264.YIFY-appletv.mp4\n": "Killing Season 2013 .mp4"
    },
    "255": {
        "Knocked.Up[2007][Unrated.Edition]DvDrip[Eng]-aXXo-appletv.mp4\n": "Knocked Up[2007][Unrated Edition][Eng].mp4"
    },
    "256": {
        "Knowing[2009]DvDrip[Eng]-FXG-appletv.mp4\n": "Knowing[2009][Eng]FXG.mp4"
    },
    "257": {
        "[Kung_Fu]_Five Deadly Venoms (1978) - Rmvb-appletv.mp4\n": "[Kung_Fu]_Five Deadly Venoms (1978) Rmvb.mp4"
    },
    "258": {
        "Kung Fu Master DVDRip Xvid AC3-THC-appletv.mp4\n": "Kung Fu Master AC3THC.mp4"
    },
    "259": {
        "Kung.Pow.Xvid.DVDrip.DS-appletv.mp4\n": "Kung Pow DS.mp4"
    },
    "260": {
        "l-127.hours.xvid-appletv.mp4\n": "l127 hours.mp4"
    },
    "261": {
        "Last.Vegas.2013.1080p.BluRay.x264.YIFY-ps3.mp4\n": "Last Vegas 2013 .mp4"
    },
    "262": {
        "Law Abiding Citizen 2009-appletv.mp4\n": "Law Abiding Citizen 2009.mp4"
    },
    "263": {
        "Left Behind I-appletv.mp4\n": "Left Behind I.mp4"
    },
    "264": {
        "Left Behind III - World at War-appletv.mp4\n": "Left Behind III World at War.mp4"
    },
    "265": {
        "Left Behind II - Tribulation Force-appletv.mp4\n": "Left Behind II Tribulation Force.mp4"
    },
    "266": {
        "Legend of the Guardians (2010) DVDRip XviD-MAXSPEED www.torentz.3xforum.ro-appletv.mp4\n": "Legend of the Guardians (2010) XviDMAXSPEED www torentz 3xforum ro.mp4"
    },
    "267": {
        "Legion (2010) R5 DVDRip XviD-MAXSPEED www.torentz.3xforum.ro-appletv.mp4\n": "Legion (2010) R5 XviDMAXSPEED www torentz 3xforum ro.mp4"
    },
    "268": {
        "Life of Pi 2012 DVDSCR-appletv.mp4\n": "Life of Pi 2012 DVDSCR.mp4"
    },
    "269": {
        "Lincoln.2012.720p.Bluray.x264.YIFY-ps3.mp4\n": "Lincoln 2012 .mp4"
    },
    "270": {
        "Little Nicky-appletv.mp4\n": "Little Nicky.mp4"
    },
    "271": {
        "Lottery Ticket.mp4\n": "Lottery Ticket.mp4"
    },
    "272": {
        "Love.and.Basketball.2000.DVDRip.DivX-appletv.mp4\n": "Love and Basketball 2000 DivX.mp4"
    },
    "273": {
        "Love Stinks-appletv3.mp4\n": "Love Stinksappletv3.mp4"
    },
    "274": {
        "Madea Goes To Jail[2009]-appletv.mp4\n": "Madea Goes To Jail[2009].mp4"
    },
    "275": {
        "Made of Honor (2008)-appletv.mp4\n": "Made of Honor (2008).mp4"
    },
    "276": {
        "Major Payne [1995]-appletv.mp4\n": "Major Payne [1995].mp4"
    },
    "277": {
        "Man.on.a.Ledge.2012.mp4\n": "Man on a Ledge 2012.mp4"
    },
    "278": {
        "man.on.fire.2004-appletv.mp4\n": "man on fire 2004.mp4"
    },
    "279": {
        "march of the penguins 2005 - zeberzee-ps3.mp4\n": "march of the penguins 2005 zeberzeeps3.mp4"
    },
    "280": {
        "Marley & Me[2008]DvDrip[Eng]-FXG-appletv.mp4\n": "Marley & Me[2008][Eng]FXG.mp4"
    },
    "281": {
        "Max.Payne[2008][Unrated.Edition]-appletv.mp4\n": "Max Payne[2008][Unrated Edition].mp4"
    },
    "282": {
        "Meet Dave (2008)-appletv.mp4\n": "Meet Dave (2008).mp4"
    },
    "283": {
        "Mission Impossible-appletv.mp4\n": "Mission Impossible.mp4"
    },
    "284": {
        "Mission Impossible II-appletv.mp4\n": "Mission Impossible II.mp4"
    },
    "285": {
        "Mission Impossible III-appletv.mp4\n": "Mission Impossible III.mp4"
    },
    "286": {
        "Monsters.2010.LiMiTED.BRRip.XviD.Feel-Free-appletv.mp4\n": "Monsters 2010 LiMiTED FeelFree.mp4"
    },
    "287": {
        "Monsters.University.2013.720p.BluRay.x264.YIFY-appletv3.mp4\n": "Monsters University 2013 appletv3.mp4"
    },
    "288": {
        "Monsters VS. Aliens-appletv.mp4\n": "Monsters VS Aliens.mp4"
    },
    "289": {
        "Mr Deeds-appletv.mp4\n": "Mr Deeds.mp4"
    },
    "290": {
        "mv\n": "mv"
    },
    "291": {
        "My Best  Friends Girl (2008)-appletv.mp4\n": "My Best Friends Girl (2008).mp4"
    },
    "292": {
        "My Best Friend's Wedding 1997 BDRip 1080p DTS HighCode.mkv\n": "My Best Friend's Wedding 1997 DTS HighCode.mkv"
    },
    "293": {
        "My.Bloody.Valentine.2008.DvDRip-FxM-appletv.mp4\n": "My Bloody Valentine 2008 DvDRipFxM.mp4"
    },
    "294": {
        "Napoleon Dynamite[2004]XviD.DvDrip -Kriegster-appletv.mp4\n": "Napoleon Dynamite[2004] Kriegster.mp4"
    },
    "295": {
        "National Treasure 2 Book of Secrets(2008)-appletv.mp4\n": "National Treasure 2 Book of Secrets(2008).mp4"
    },
    "296": {
        "Never Back Down (2008)-appletv.mp4\n": "Never Back Down (2008).mp4"
    },
    "297": {
        "Never been kissed-appletv.mp4\n": "Never been kissed.mp4"
    },
    "298": {
        "Next[2007]-appletv.mp4\n": "Next[2007].mp4"
    },
    "299": {
        "Next Day Air [2009]-appletv.mp4\n": "Next Day Air [2009].mp4"
    },
    "300": {
        "Next.Friday.2000.XViD-SwP-appletv.mp4\n": "Next Friday 2000 XViDSwP.mp4"
    },
    "301": {
        "Nick and Norahs Infinite Playlist[2008]-appletv.mp4\n": "Nick and Norahs Infinite Playlist[2008].mp4"
    },
    "302": {
        "Night.At.The.Museum[2006]DvDrip[Eng]-aXXo-appletv.mp4\n": "Night At The Museum[2006][Eng].mp4"
    },
    "303": {
        "Night.At.The.Museum.Battle.Of.The.Smithsonian.2009.DvDRip-FxM-appletv.mp4\n": "Night At The Museum Battle Of The Smithsonian 2009 DvDRipFxM.mp4"
    },
    "304": {
        "Night.Of.The.Living.Dead.1990.DVDRip.XViD-AssMaster-appletv.mp4\n": "Night Of The Living Dead 1990 XViDAssMaster.mp4"
    },
    "305": {
        "Night Of The Living Dead - 30th Anniversary Edition-appletv.mp4\n": "Night Of The Living Dead 30th Anniversary Edition.mp4"
    },
    "306": {
        "Nitro.Circus.The.Movie.2012.BRRip.XviD.Ac3-Blackjesus-appletv.mp4\n": "Nitro Circus The Movie 2012 Ac3Blackjesus.mp4"
    },
    "307": {
        "Not Another Teen Movie[ENG][2001] -Jns-appletv.mp4\n": "Not Another Teen Movie[ENG][2001] Jns.mp4"
    },
    "308": {
        "Notorious[2009]DvDrip[Eng]-FXG-appletv.mp4\n": "Notorious[2009][Eng]FXG.mp4"
    },
    "309": {
        "Oblivion.2013.1080p.BluRay.x264.YIFY-appletv.mp4\n": "Oblivion 2013 .mp4"
    },
    "310": {
        "Obsessed-appletv.mp4\n": "Obsessed.mp4"
    },
    "311": {
        "Oceans.13.(2007)-appletv.mp4\n": "Oceans 13 (2007).mp4"
    },
    "312": {
        "Oceans Eleven-appletv.mp4\n": "Oceans Eleven.mp4"
    },
    "313": {
        "Oceans Twelve-appletv.mp4\n": "Oceans Twelve.mp4"
    },
    "314": {
        "Office Space [Special Edition]-appletv.mp4\n": "Office Space [Special Edition].mp4"
    },
    "315": {
        "Old School.mp4\n": "Old School.mp4"
    },
    "316": {
        "Olympus.Has.Fallen.2013.1080p.BluRay.x264.YIFY-appletv3.mp4\n": "Olympus Has Fallen 2013 appletv3.mp4"
    },
    "317": {
        "Olympus.Has.Fallen.2013.1080p.BluRay.x264.YIFY-appletv.mp4\n": "Olympus Has Fallen 2013 .mp4"
    },
    "318": {
        "Orphan Pt 1-appletv.mp4\n": "Orphan Pt 1.mp4"
    },
    "319": {
        "Orphan Pt 2-appletv.mp4\n": "Orphan Pt 2.mp4"
    },
    "320": {
        "Our Idiot Brother-appletv.mp4\n": "Our Idiot Brother.mp4"
    },
    "321": {
        "Over.The.Hedge[2006]DvDrip.AC3[Eng]-aXXo-appletv.mp4\n": "Over The Hedge[2006] [Eng].mp4"
    },
    "322": {
        "Oz the Great and Powerful 2013.720p.BluRay.x264.YIFY-appletv.mp4\n": "Oz the Great and Powerful 2013 .mp4"
    },
    "323": {
        "Pain.&.Gain.2013.720p.BluRay.x264.YIFY-appletv.mp4\n": "Pain & Gain 2013 .mp4"
    },
    "324": {
        "Paranorman.2012.720p.BrRip.x264.YIFY-appletv.mp4\n": "Paranorman 2012 .mp4"
    },
    "325": {
        "Paul Blart Mall Cop[2009]DvDrip[Eng]-FXG-appletv.mp4\n": "Paul Blart Mall Cop[2009][Eng]FXG.mp4"
    },
    "326": {
        "Perfume-The Story of a Murderer-appletv.mp4\n": "PerfumeThe Story of a Murderer.mp4"
    },
    "327": {
        "Pineapple Express(2008)DVDSCR-appletv.mp4\n": "Pineapple Express(2008)DVDSCR.mp4"
    },
    "328": {
        "Pirates of the Caribbean On Stranger Tides (2011)-appletv.mp4\n": "Pirates of the Caribbean On Stranger Tides (2011).mp4"
    },
    "329": {
        "Pitch Black-appletv.mp4\n": "Pitch Black.mp4"
    },
    "330": {
        "Pitch.Perfect.2012.720p.BRrip.264.YIFY-appletv.mp4\n": "Pitch Perfect 2012 264.mp4"
    },
    "331": {
        "Poetic.Justice[1993]DvDrip[Eng]-t7LC-appletv.mp4\n": "Poetic Justice[1993][Eng]t7LC.mp4"
    },
    "332": {
        "Pokemon.Detective.Pikachu.2019.1080p.HDRip.x264.AAC2.0-STUTTERSHIT.mkv\n": "Pokemon Detective Pikachu 2019 HDRip AAC2 0STUTTERSHIT.mkv"
    },
    "333": {
        "Precious Based on the Novel Push by Sapphire-appletv.mp4\n": "Precious Based on the Novel Push by Sapphire.mp4"
    },
    "334": {
        "Pretty Woman 1990 Richard Gere Julia Roberts Comedy Romance51.mp4\n": "Pretty Woman 1990 Richard Gere Julia Roberts Comedy Romance51.mp4"
    },
    "335": {
        "Priest.2011.R5.LiNE.AC3.XViD-EP1C-appletv.mp4\n": "Priest 2011 R5 LiNE XViDEP1C.mp4"
    },
    "336": {
        "Prince of Persia The Sands of Time 2010.mp4\n": "Prince of Persia The Sands of Time 2010.mp4"
    },
    "337": {
        "Prisoners.2013.720p.BluRay.x264.YIFY-appletv3.mp4\n": "Prisoners 2013 appletv3.mp4"
    },
    "338": {
        "Prom Night (2008)-appletv.mp4\n": "Prom Night (2008).mp4"
    },
    "339": {
        "Public Enemies-appletv.mp4\n": "Public Enemies.mp4"
    },
    "340": {
        "Pulp Fiction -appletv.mp4\n": "Pulp Fiction.mp4"
    },
    "341": {
        "pure luck 1991 dvdrip xvid req-appletv.mp4\n": "pure luck 1991 req.mp4"
    },
    "342": {
        "Push.2009.HDRip.XviD-NoRARs\u00e2\u201e\u00a2-appletv.mp4\n": "Push 2009 HDRip XviDNoRARs\u00e2\u201e\u00a2.mp4"
    },
    "343": {
        "Race To Witch Mountain [2009]-appletv.mp4\n": "Race To Witch Mountain [2009].mp4"
    },
    "344": {
        "Radio-appletv.mp4\n": "Radio.mp4"
    },
    "345": {
        "Ray[Ray Charles]-DVDrip[2004]-appletv.mp4\n": "Ray[Ray Charles][2004].mp4"
    },
    "346": {
        "Redbelt (2008)-appletv.mp4\n": "Redbelt (2008).mp4"
    },
    "347": {
        "Remember the Titans[2000]DvDrip[Eng]-prithwi-appletv.mp4\n": "Remember the Titans[2000][Eng]prithwi.mp4"
    },
    "348": {
        "Resident.Evil.2-Apocalypse[2004]DvDrip-aXXo-appletv.mp4\n": "Resident Evil 2Apocalypse[2004]DvDripaXXo.mp4"
    },
    "349": {
        "Resident.Evil.3-Extinction[2007]DvDrip-aXXo-appletv.mp4\n": "Resident Evil 3Extinction[2007]DvDripaXXo.mp4"
    },
    "350": {
        "Resident Evil Afterlife (2010) R5 XviD-MAXSPEED www.torentz.3xforum.ro-appletv.mp4\n": "Resident Evil Afterlife (2010) R5 XviDMAXSPEED www torentz 3xforum ro.mp4"
    },
    "351": {
        "Resident.Evil-Degeneration[2008]-appletv.mp4\n": "Resident EvilDegeneration[2008].mp4"
    },
    "352": {
        "Ride.Along.2014.1080p.WEB-DL.H264-PublicHD-ps3.mp4\n": "Ride Along 2014 WEBDL H264PublicHDps3.mp4"
    },
    "353": {
        "Rio (2011) R5 XviD-MAXSPEED www.torentz.3xforum.ro-appletv.mp4\n": "Rio (2011) R5 XviDMAXSPEED www torentz 3xforum ro.mp4"
    },
    "354": {
        "Road Trip Beer Pong [2009]-appletv.mp4\n": "Road Trip Beer Pong [2009].mp4"
    },
    "355": {
        "Robot and Frank-appletv.mp4\n": "Robot and Frank.mp4"
    },
    "356": {
        "RocknRolla[2008]-appletv.mp4\n": "RocknRolla[2008].mp4"
    },
    "357": {
        "Role.Models[2008]-appletv.mp4\n": "Role Models[2008].mp4"
    },
    "358": {
        "roor-thefighters2-xvid-appletv.mp4\n": "roorthefighters2xvid.mp4"
    },
    "359": {
        "Run Fatboy Run (2007)-appletv.mp4\n": "Run Fatboy Run (2007).mp4"
    },
    "360": {
        "Rush.2013.1080p.BluRay.x264.YIFY-ps3.mp4\n": "Rush 2013 .mp4"
    },
    "361": {
        "Salt Director's Cut.mp4\n": "Salt Director's Cut.mp4"
    },
    "362": {
        "santi-ipman2.brrip.xvid-appletv.mp4\n": "santiipman2 .mp4"
    },
    "363": {
        "Save.The.Last.Dance[2001]DVDrip[ENG]-MissRipZ-appletv.mp4\n": "Save The Last Dance[2001][ENG]MissRipZ.mp4"
    },
    "364": {
        "Saving Private Ryan [1999]-appletv.mp4\n": "Saving Private Ryan [1999].mp4"
    },
    "365": {
        "Scarface[1983][Uncut.Version]DvDrip[eng]-appletv.mp4\n": "Scarface[1983][Uncut Version][eng].mp4"
    },
    "366": {
        "Scary.MoVie.2013.720p.BluRay.x264.YIFY-appletv3.mp4\n": "Scary MoVie 2013 appletv3.mp4"
    },
    "367": {
        "Scary Movie 2-appletv.mp4\n": "Scary Movie 2.mp4"
    },
    "368": {
        "Scary Movie 3-appletv.mp4\n": "Scary Movie 3.mp4"
    },
    "369": {
        "Scary Movie-appletv.mp4\n": "Scary Movie.mp4"
    },
    "370": {
        "School Of Rock-appletv.mp4\n": "School Of Rock.mp4"
    },
    "371": {
        "Scott Pilgrim vs the World [2010]-appletv.mp4\n": "Scott Pilgrim vs the World [2010].mp4"
    },
    "372": {
        "Senseless [1998]-appletv.mp4\n": "Senseless [1998].mp4"
    },
    "373": {
        "Set It Off 1996.mp4\n": "Set It Off 1996.mp4"
    },
    "374": {
        "Seven Pounds Pt1-appletv.mp4\n": "Seven Pounds Pt1.mp4"
    },
    "375": {
        "Seven Pounds Pt2-appletv.mp4\n": "Seven Pounds Pt2.mp4"
    },
    "376": {
        "seven.psychopaths.2012.720p.bluray.x264-sparks-appletv.mp4\n": "seven psychopaths 2012 x264sparks.mp4"
    },
    "377": {
        "Sex and the City The Movie (2008)-appletv.mp4\n": "Sex and the City The Movie (2008).mp4"
    },
    "378": {
        "Sex.Drive[2008][Unrated.Edition]DvDrip-aXXo-appletv.mp4\n": "Sex Drive[2008][Unrated Edition]DvDripaXXo.mp4"
    },
    "379": {
        "Shallow Hal-appletv.mp4\n": "Shallow Hal.mp4"
    },
    "380": {
        "Shaun of the Dead-MitZep-appletv.mp4\n": "Shaun of the DeadMitZep.mp4"
    },
    "381": {
        "Sherlock Holmes[2009]DvDrip[Eng]-FXG-appletv.mp4\n": "Sherlock Holmes[2009][Eng]FXG.mp4"
    },
    "382": {
        "Shooter[2007]DvDrip[Eng]-aXXo-appletv.mp4\n": "Shooter[2007][Eng].mp4"
    },
    "383": {
        "Shottas-appletv.mp4\n": "Shottas.mp4"
    },
    "384": {
        "Shutter (2008)-appletv.mp4\n": "Shutter (2008).mp4"
    },
    "385": {
        "Side.Effects.2013.720p.BluRay.x264.YIFY-appletv.mp4\n": "Side Effects 2013 .mp4"
    },
    "386": {
        "Silver.Linings.Playbook.2012.1080p.x264.YIFY-appletv.mp4\n": "Silver Linings Playbook 2012 .mp4"
    },
    "387": {
        "Skyfall.2012.1080p.BrRip.x264.YIFY-appletv.mp4\n": "Skyfall 2012 .mp4"
    },
    "388": {
        "Slumdog.Millionaire.DVDSCR.XviD-NoGrp-appletv.mp4\n": "Slumdog Millionaire DVDSCR XviDNoGrp.mp4"
    },
    "389": {
        "Snitch.2013.720p.BluRay.x264.YIFY-appletv.mp4\n": "Snitch 2013 .mp4"
    },
    "390": {
        "Soul Plane-appletv.mp4\n": "Soul Plane.mp4"
    },
    "391": {
        "Source.Code.2011.BRRip.READNFO.XViD-TDP-appletv.mp4\n": "Source Code 2011 READNFO XViDTDP.mp4"
    },
    "392": {
        "Space_Jam-appletv.mp4\n": "Space_Jam.mp4"
    },
    "393": {
        "Speed Racer (2008)-appletv.mp4\n": "Speed Racer (2008).mp4"
    },
    "394": {
        "Star.Trek.Beyond.2016.HDRip.XviD.AC3-EVO.avi\n": "Star Trek Beyond 2016 HDRip AC3EVO.avi"
    },
    "395": {
        "Stealth[2005]DvDrip[Eng]-aXXo-appletv.mp4\n": "Stealth[2005][Eng].mp4"
    },
    "396": {
        "Stealth[2005]DvDrip[Eng]-aXXo.avi\n": "Stealth[2005][Eng].avi"
    },
    "397": {
        "Step Brothers(2008)-appletv.mp4\n": "Step Brothers(2008).mp4"
    },
    "398": {
        "Stephen King's.IT.DVDrip.(720x480 WS)-appletv.mp4\n": "Stephen King's IT (720x480 WS).mp4"
    },
    "399": {
        "Step Up 1 2006.mp4\n": "Step Up 1 2006.mp4"
    },
    "400": {
        "Step Up 2 The Streets (2008)-appletv.mp4\n": "Step Up 2 The Streets (2008).mp4"
    },
    "401": {
        "Step Up 3D 2010.720p.BrRip.x264.YIFY-appletv.mp4\n": "Step Up 3D 2010 .mp4"
    },
    "402": {
        "Step Up 4 2012 Revolution.mp4\n": "Step Up 4 2012 Revolution.mp4"
    },
    "403": {
        "Step.Up.All.In.2014.720p.BluRay.x264.YIFY.mp4\n": "Step Up All In 2014 .mp4"
    },
    "404": {
        "Stick.It[2006]DvDrip[Eng]-aXXo-appletv.mp4\n": "Stick It[2006][Eng].mp4"
    },
    "405": {
        "Street Kings (2008)-appletv.mp4\n": "Street Kings (2008).mp4"
    },
    "406": {
        "Sucker Punch (2011) DVDRip XviD-MAXSPEED www.torentz.3xforum.ro-appletv.mp4\n": "Sucker Punch (2011) XviDMAXSPEED www torentz 3xforum ro.mp4"
    },
    "407": {
        "Suicide.Squad.2016.HC.HDRip.XViD.AC3-ETRG.avi\n": "Suicide Squad 2016 HC HDRip AC3ETRG.avi"
    },
    "408": {
        "Superbad Pt.I (2008)-appletv.mp4\n": "Superbad Pt I (2008).mp4"
    },
    "409": {
        "Superbad Pt.II (2008)-appletv.mp4\n": "Superbad Pt II (2008).mp4"
    },
    "410": {
        "Superhero.Movie[2008]DvDrip.AC3-aXXo-appletv.mp4\n": "Superhero Movie[2008] AC3aXXo.mp4"
    },
    "411": {
        "Superstar Pt1-appletv.mp4\n": "Superstar Pt1.mp4"
    },
    "412": {
        "Superstar Pt2-appletv.mp4\n": "Superstar Pt2.mp4"
    },
    "413": {
        "Super Troopers-appletv.mp4\n": "Super Troopers.mp4"
    },
    "414": {
        "surrogates-appletv.mp4\n": "surrogates.mp4"
    },
    "415": {
        "Taken[2008]-appletv.mp4\n": "Taken[2008].mp4"
    },
    "416": {
        "Tales.From.The.Hood.DVDRip.iNT.x264-JiZZA.mp4\n": "Tales From The Hood iNT x264JiZZA.mp4"
    },
    "417": {
        "Talladega.Nights[2006][Unrated.Edition]DvDrip[Eng]-aXXo-appletv.mp4\n": "Talladega Nights[2006][Unrated Edition][Eng].mp4"
    },
    "418": {
        "tdm-ob2a-appletv.mp4\n": "tdmob2a.mp4"
    },
    "419": {
        "tdm-ob2b-appletv.mp4\n": "tdmob2b.mp4"
    },
    "420": {
        "Team America - World Police XviD MP3 DVD-Rip-appletv.mp4\n": "Team America World Police MP3.mp4"
    },
    "421": {
        "Terminator.2-Judgment.Day[1991]DvDrip-aXXo-appletv.mp4\n": "Terminator 2Judgment Day[1991]DvDripaXXo.mp4"
    },
    "422": {
        "Terminator.3-Rise.Of.The.Machines[2003]DvDrip-aXXo-appletv.mp4\n": "Terminator 3Rise Of The Machines[2003]DvDripaXXo.mp4"
    },
    "423": {
        "Terminator.Salvation.2009.DvDRip-FxM-appletv.mp4\n": "Terminator Salvation 2009 DvDRipFxM.mp4"
    },
    "424": {
        "That.Awkward.Moment.2014.720p.BluRay.x264.YIFY-ps3.mp4\n": "That Awkward Moment 2014 .mp4"
    },
    "425": {
        "The.40.Year.Old.Virgin.Unrated.2005.720p.BluRay.x264.YIFY-ps3.mp4\n": "The 40 Year Old Virgin Unrated 2005 .mp4"
    },
    "426": {
        "The 6th Man 1997 DvDrip[Eng]-greenbud1969-appletv.mp4\n": "The 6th Man 1997 [Eng]greenbud1969.mp4"
    },
    "427": {
        "The Addams Family-appletv.mp4\n": "The Addams Family.mp4"
    },
    "428": {
        "The Adjustment Bureau (2011) DVDRip XviD-MAXSPEED www.torentz.3xforum.ro-appletv.mp4\n": "The Adjustment Bureau (2011) XviDMAXSPEED www torentz 3xforum ro.mp4"
    },
    "429": {
        "The.Amazing.Spiderman.2012.1080p.BrRip.x264.YIFY-appletv3.mp4\n": "The Amazing Spiderman 2012 appletv3.mp4"
    },
    "430": {
        "The.Avengers.2012.720p.BluRay.x264.YIFY.mp4\n": "The Avengers 2012 .mp4"
    },
    "431": {
        "The Bank Job-appletv.mp4\n": "The Bank Job.mp4"
    },
    "432": {
        "The Best Man Holiday [2013] HC WEBRip XViD[AC3]-juggs[ETRG]-appletv3.mp4\n": "The Best Man Holiday [2013] HC WEBRip []juggs[ETRG]appletv3.mp4"
    },
    "433": {
        "The Bone Collector-appletv.mp4\n": "The Bone Collector.mp4"
    },
    "434": {
        "The Bourne Identity 2002-appletv.mp4\n": "The Bourne Identity 2002.mp4"
    },
    "435": {
        "The Bourne Supremacy 2004-appletv.mp4\n": "The Bourne Supremacy 2004.mp4"
    },
    "436": {
        "The Bourne Ultimatum 2007-appletv.mp4\n": "The Bourne Ultimatum 2007.mp4"
    },
    "437": {
        "The.Butler.2013.720p.BluRay.x264.YIFY-ps3.mp4\n": "The Butler 2013 .mp4"
    },
    "438": {
        "The.Call.2013.720p.BluRay.x264.YIFY-appletv.mp4\n": "The Call 2013 .mp4"
    },
    "439": {
        "The Children Of Huang Shi (2008)-appletv.mp4\n": "The Children Of Huang Shi (2008).mp4"
    },
    "440": {
        "The.Clinic.2010.DVDRip.XviD-NoGRP-appletv.mp4\n": "The Clinic 2010 XviDNoGRP.mp4"
    },
    "441": {
        "The Craft Special Edition 1996 DvDrip[Eng]-greenbud1969-appletv.mp4\n": "The Craft Special Edition 1996 [Eng]greenbud1969.mp4"
    },
    "442": {
        "The Curious Case of Benjamin Button DVDSCR(2008)-appletv.mp4\n": "The Curious Case of Benjamin Button DVDSCR(2008).mp4"
    },
    "443": {
        "The Dark Knight(2008)-appletv.mp4\n": "The Dark Knight(2008).mp4"
    },
    "444": {
        "The.Dark.Knight.Rises.2012.1080p.BluRay.x264.YIFY-appletv.mp4\n": "The Dark Knight Rises 2012 .mp4"
    },
    "445": {
        "The Dark KNight Rises.CD1-appletv.mp4\n": "The Dark KNight Rises CD1.mp4"
    },
    "446": {
        "The Dark Knight Rises.cd2-appletv.mp4\n": "The Dark Knight Rises cd2.mp4"
    },
    "447": {
        "The Day The Earth Stood Still[2008]-appletv.mp4\n": "The Day The Earth Stood Still[2008].mp4"
    },
    "448": {
        "The.Devil's.Advocate.720p.HDTV.x264.YIFY-appletv.mp4\n": "The Devil's Advocate HDTV .mp4"
    },
    "449": {
        "The Eye (2008)-appletv.mp4\n": "The Eye (2008).mp4"
    },
    "450": {
        "The.Family.Stone[2005]DvDrip[Eng]-aXXo-appletv.mp4\n": "The Family Stone[2005][Eng].mp4"
    },
    "451": {
        "The Fast & The Furious part 1-appletv.mp4\n": "The Fast & The Furious part 1.mp4"
    },
    "452": {
        "The Fast & The Furious part 2-appletv.mp4\n": "The Fast & The Furious part 2.mp4"
    },
    "453": {
        "The.Fighter.2010.1080p.BluRay.x264.YIFY.mp4\n": "The Fighter 2010 .mp4"
    },
    "454": {
        "The Five Heartbeats A-appletv-appletv.mp4\n": "The Five Heartbeats A.mp4"
    },
    "455": {
        "The Five Heartbeats B-appletv-appletv.mp4\n": "The Five Heartbeats B.mp4"
    },
    "456": {
        "The Girlfriend Experience[2009]-appletv.mp4\n": "The Girlfriend Experience[2009].mp4"
    },
    "457": {
        "The Goods Live Hard Sell Hard-appletv.mp4\n": "The Goods Live Hard Sell Hard.mp4"
    },
    "458": {
        "The.Great.Gatsby.2013.720p.BluRay.x264.YIFY-appletv.mp4\n": "The Great Gatsby 2013 .mp4"
    },
    "459": {
        "The Grudge [2004]DvDrip[Eng]-[ICEMAN][h33t]-appletv.mp4\n": "The Grudge [2004][Eng][ICEMAN][h33t].mp4"
    },
    "460": {
        "The Grudge 2[2006]DvDrip[Eng]-[ICEMAN][h33t]-appletv.mp4\n": "The Grudge 2[2006][Eng][ICEMAN][h33t].mp4"
    },
    "461": {
        "The Grudge 3 [2009]DvDrip[Eng]-[ICEMAN][h33t]-appletv.mp4\n": "The Grudge 3 [2009][Eng][ICEMAN][h33t].mp4"
    },
    "462": {
        "The Haunting in Connecticut[2009]-appletv.mp4\n": "The Haunting in Connecticut[2009].mp4"
    },
    "463": {
        "The Hobbit The Desolation of Smaug (2013) DVDSCR-ps3.mp4\n": "The Hobbit The Desolation of Smaug (2013) DVDSCRps3.mp4"
    },
    "464": {
        "The.Holiday[2006]DvDrip[Eng]-aXXo-appletv.mp4\n": "The Holiday[2006][Eng].mp4"
    },
    "465": {
        "The Host 2013 720p HDRip x264 AC3-JYK-appletv.m4v\n": "The Host 2013 HDRip AC3JYK.m4v"
    },
    "466": {
        "The.Hunger.Games.Catching.Fire.2013.1080p.BluRay.x264.YIFY-ps3.mp4\n": "The Hunger Games Catching Fire 2013 .mp4"
    },
    "467": {
        "The Hurt Locker (2009) DVDR DivXNL-Team-appletv.mp4\n": "The Hurt Locker (2009) DVDR DivXNLTeam.mp4"
    },
    "468": {
        "The Incredible Hulk(2008)-appletv.mp4\n": "The Incredible Hulk(2008).mp4"
    },
    "469": {
        "The.Internship.2013.720p.BluRay.x264.YIFY-appletv3.mp4\n": "The Internship 2013 appletv3.mp4"
    },
    "470": {
        "The Kingdom[2007]DvDrip[Eng]-FXG-appletv.mp4\n": "The Kingdom[2007][Eng]FXG.mp4"
    },
    "471": {
        "The.Lake.House[2006]DvDrip[Eng]-aXXo-appletv.mp4\n": "The Lake House[2006][Eng].mp4"
    },
    "472": {
        "The Last Samauri-appletv.mp4\n": "The Last Samauri.mp4"
    },
    "473": {
        "The Last Witch Hunter 2015 1080p BluRay x264 DTS-JYK.mkv\n": "The Last Witch Hunter 2015 .mkv"
    },
    "474": {
        "The.Legend.of.Tarzan.2016.HC.HDRip.XviD.AC3-EVO.avi\n": "The Legend of Tarzan 2016 HC HDRip AC3EVO.avi"
    },
    "475": {
        "The.Lego.Movie.2014.720p.BluRay.x264.YIFY-ps3.mp4\n": "The Lego Movie 2014 .mp4"
    },
    "476": {
        "The Lincoln Lawyer-appletv.mp4\n": "The Lincoln Lawyer.mp4"
    },
    "477": {
        "The.Longest.Yard[2005]DvDrip[Eng]-aXXo-appletv.mp4\n": "The Longest Yard[2005][Eng].mp4"
    },
    "478": {
        "The.Lost.World-Jurassic.Park[1997]DvDrip-aXXo-appletv.mp4\n": "The Lost WorldJurassic Park[1997]DvDripaXXo.mp4"
    },
    "479": {
        "The Lovely Bones[2009]DvDrip[Eng]-FXG-appletv.mp4\n": "The Lovely Bones[2009][Eng]FXG.mp4"
    },
    "480": {
        "The.Man.Who.Knew.Infinity.2015.BRRip.XViD-ETRG.avi\n": "The Man Who Knew Infinity 2015 XViDETRG.avi"
    },
    "481": {
        "The.Man.with.the.Iron.Fists.2012.UNRATED.1080p.x264.YIFY-appletv.mp4\n": "The Man with the Iron Fists 2012 UNRATED .mp4"
    },
    "482": {
        "The Meteor Man-appletv.mp4\n": "The Meteor Man.mp4"
    },
    "483": {
        "The Mummy 1999.720p.BrRip.x264.YIFY-appletv.mp4\n": "The Mummy 1999 .mp4"
    },
    "484": {
        "The.Mummy.Returns[2001]DvDrip.AC3[Eng][Multi-Sub]-Vex-appletv.mp4\n": "The Mummy Returns[2001] [Eng][MultiSub]Vex.mp4"
    },
    "485": {
        "The.Mummy-Tomb.Of.The.Dragon.Emperor[2008]-appletv.mp4\n": "The MummyTomb Of The Dragon Emperor[2008].mp4"
    },
    "486": {
        "The Notebook (2004)-appletv.mp4\n": "The Notebook (2004).mp4"
    },
    "487": {
        "The Numer 23-appletv.mp4\n": "The Numer 23.mp4"
    },
    "488": {
        "The Nut Job 2014 1080p BRRip x264 AC3-JYK-ps3.mp4\n": "The Nut Job 2014 AC3JYKps3.mp4"
    },
    "489": {
        "The One-appletv.mp4\n": "The One.mp4"
    },
    "490": {
        "The Other Guys[2010]-appletv.mp4\n": "The Other Guys[2010].mp4"
    },
    "491": {
        "The Passion of the Christ KLAXXON-appletv.mp4\n": "The Passion of the Christ KLAXXON.mp4"
    },
    "492": {
        "The.Perks.of.Being.a.Wallflower.2012.720p.BRrip.x264.GAZ.YIFY-appletv.mp4\n": "The Perks of Being a Wallflower 2012 GAZ.mp4"
    },
    "493": {
        "The Pest-appletv.mp4\n": "The Pest.mp4"
    },
    "494": {
        "The Pianist-appletv.mp4\n": "The Pianist.mp4"
    },
    "495": {
        "The Pirates of Silicon Valley(1999)-appletv.mp4\n": "The Pirates of Silicon Valley(1999).mp4"
    },
    "496": {
        "The Prince of Egypt-appletv.mp4\n": "The Prince of Egypt.mp4"
    },
    "497": {
        "The.Princess.Diaries.2001.BluRay.720p.H264-appletv.mp4\n": "The Princess Diaries 2001 H264.mp4"
    },
    "498": {
        "The Princess' Diaries 2-appletv.mp4\n": "The Princess' Diaries 2.mp4"
    },
    "499": {
        "The Proposal[2009]DvDrip[Eng]-FXG-appletv.mp4\n": "The Proposal[2009][Eng]FXG.mp4"
    },
    "500": {
        "The.Pursuit.Of.Happyness.2006.1080p.BrRip.x264.YIFY-appletv3.mp4\n": "The Pursuit Of Happyness 2006 appletv3.mp4"
    },
    "501": {
        "The Ref 1994 XviD DvDrip[Eng]-greenbud1969-appletv.mp4\n": "The Ref 1994 [Eng]greenbud1969.mp4"
    },
    "502": {
        "The Ruins (2008)-appletv.mp4\n": "The Ruins (2008).mp4"
    },
    "503": {
        "The Sandlot-appletv.mp4\n": "The Sandlot.mp4"
    },
    "504": {
        "The Shawshank Redemption (1994) [1080p] x264 - Jalucian-ps3.mp4\n": "The Shawshank Redemption (1994) [] Jalucianps3.mp4"
    },
    "505": {
        "The Sixth Sense-appletv.mp4\n": "The Sixth Sense.mp4"
    },
    "506": {
        "The Soloist.2009-appletv.mp4\n": "The Soloist 2009.mp4"
    },
    "507": {
        "The.Sorcerer.And.The.White.Snake.2011.720p.BDRip.XviD.AC3-ViSiON-appletv.mp4\n": "The Sorcerer And The White Snake 2011 AC3ViSiON.mp4"
    },
    "508": {
        "The Spirit[2008]DvDrip[Eng]-FXG-appletv.mp4\n": "The Spirit[2008][Eng]FXG.mp4"
    },
    "509": {
        "The Strangers[2008][Unrated Edition]DvDrip[Eng]-FXG-appletv.mp4\n": "The Strangers[2008][Unrated Edition][Eng]FXG.mp4"
    },
    "510": {
        "The Temptations (1998)-appletv.mp4\n": "The Temptations (1998).mp4"
    },
    "511": {
        "The.Terminator[1984]DvDrip-aXXo-appletv.mp4\n": "The Terminator[1984]DvDripaXXo.mp4"
    },
    "512": {
        "The.Tourist.2010.TS.XviD.Feel-Free-appletv.mp4\n": "The Tourist 2010 TS FeelFree.mp4"
    },
    "513": {
        "The Truman Show-appletv.mp4\n": "The Truman Show.mp4"
    },
    "514": {
        "The.Unborn.INTERNAL.R5.LINE.XViD-mVs-appletv.mp4\n": "The Unborn INTERNAL R5 LINE XViDmVs.mp4"
    },
    "515": {
        "The Vow(2012)-appletv.mp4\n": "The Vow(2012).mp4"
    },
    "516": {
        "The Watch 2012 720p HDrip AC3-ViBE-appletv.mp4\n": "The Watch 2012 HDrip AC3ViBE.mp4"
    },
    "517": {
        "The Wedding Date 2005 DVDRip Xvid AC3-Anarchy-appletv.mp4\n": "The Wedding Date 2005 AC3Anarchy.mp4"
    },
    "518": {
        "The.Wolverine.2013.mp4\n": "The Wolverine 2013.mp4"
    },
    "519": {
        "The Wood-appletv.mp4\n": "The Wood.mp4"
    },
    "520": {
        "Think.Like.a.Man.Too.2014.720p.BluRay.x264.YIFY.mp4\n": "Think Like a Man Too 2014 .mp4"
    },
    "521": {
        "This Is 40 DVD Screener 2012-appletv.mp4\n": "This Is 40 DVD Screener 2012.mp4"
    },
    "522": {
        "Thor.2011.720p.BrRip.264.YIFY.mp4\n": "Thor 2011 264.mp4"
    },
    "523": {
        "Thor.The.Dark.World.2013.720p.BluRay.x264.YIFY.mp4\n": "Thor The Dark World 2013 .mp4"
    },
    "524": {
        "Thor.The.Dark.World.2013.720p.WEB-DL.H264-WEBiOS-ps3.mp4\n": "Thor The Dark World 2013 WEBDL H264WEBiOSps3.mp4"
    },
    "525": {
        "Titanic [1997]- keltz-appletv.mp4\n": "Titanic [1997] keltz.mp4"
    },
    "526": {
        "Torque.2004.720p.BluRay.x264.YIFY.mp4\n": "Torque 2004 .mp4"
    },
    "527": {
        "TORQUE[2004]DvDrip[Eng]-NikonXp-appletv.mp4\n": "TORQUE[2004][Eng]NikonXp.mp4"
    },
    "528": {
        "Total.Recall.2012.DVDRip.XviD-Lum1x-appletv.mp4\n": "Total Recall 2012 XviDLum1x.mp4"
    },
    "529": {
        "Trainwreck.2015.UNRATED.HDRip.XViD-ETRG.avi\n": "Trainwreck 2015 UNRATED HDRip XViDETRG.avi"
    },
    "530": {
        "Traitor[2008]-appletv.mp4\n": "Traitor[2008].mp4"
    },
    "531": {
        "Transformers Revenge of the Fallen[2009]-appletv.mp4\n": "Transformers Revenge of the Fallen[2009].mp4"
    },
    "532": {
        "Transporter 3(2008)-appletv.mp4\n": "Transporter 3(2008).mp4"
    },
    "533": {
        "Tristan and Isolde[2006]-appletv.mp4\n": "Tristan and Isolde[2006].mp4"
    },
    "534": {
        "Tropic Thunder (2008)-appletv.mp4\n": "Tropic Thunder (2008).mp4"
    },
    "535": {
        "Troy-appletv.mp4\n": "Troy.mp4"
    },
    "536": {
        "True.Lies.1994.720p.x264.YIFY-appletv3.mp4\n": "True Lies 1994 appletv3.mp4"
    },
    "537": {
        "Turbo.2013.720p.BluRay.x264.YIFY-appletv3.mp4\n": "Turbo 2013 appletv3.mp4"
    },
    "538": {
        "Two Can Play That Game-appletv.mp4\n": "Two Can Play That Game.mp4"
    },
    "539": {
        "UFC.135.Jones.vs.Rampage.24.Sept.2011.HDTV.x264-Sir.Paul-appletv.mp4\n": "UFC 135 Jones vs Rampage 24 Sept 2011 HDTV x264Sir Paul.mp4"
    },
    "540": {
        "UFC.136.Edgar.v.Maynard.III.8th.Oct.2011.HDTV.x264-Sir.Paul-appletv.mp4\n": "UFC 136 Edgar v Maynard III 8th Oct 2011 HDTV x264Sir Paul.mp4"
    },
    "541": {
        "UFC.147.Franklin.vs.Silva.II.23rd.June.2012.HDTV.x264-Sir.Paul-appletv.mp4\n": "UFC 147 Franklin vs Silva II 23rd June 2012 HDTV x264Sir Paul.mp4"
    },
    "542": {
        "Underworld 3-appletv.mp4\n": "Underworld 3.mp4"
    },
    "543": {
        "Unknown (2011) DVDRip XviD-MAXSPEED www.torentz.3xforum.ro-appletv.mp4\n": "Unknown (2011) XviDMAXSPEED www torentz 3xforum ro.mp4"
    },
    "544": {
        "Unstoppable (2010) DVDRip-appletv.mp4\n": "Unstoppable (2010).mp4"
    },
    "545": {
        "Untraceable(2008)-appletv.mp4\n": "Untraceable(2008).mp4"
    },
    "546": {
        "Upside.Down.2012.720p.BluRay.x264.YIFY-appletv.mp4\n": "Upside Down 2012 .mp4"
    },
    "547": {
        "Valentine's Day[2010]DvDrip[Eng]-FXG-appletv.mp4\n": "Valentine's Day[2010][Eng]FXG.mp4"
    },
    "548": {
        "Valkerie [2009]-appletv.mp4\n": "Valkerie [2009].mp4"
    },
    "549": {
        "Vertical Limit [2000]-appletv.mp4\n": "Vertical Limit [2000].mp4"
    },
    "550": {
        "Waist Deep 2006 [DVDRip.XviD-miguel] [ENG]-appletv.mp4\n": "Waist Deep 2006 [ XviDmiguel] [ENG].mp4"
    },
    "551": {
        "Wanted (2008)-appletv.mp4\n": "Wanted (2008).mp4"
    },
    "552": {
        "Waterboy(199$)-appletv.mp4\n": "Waterboy(199$).mp4"
    },
    "553": {
        "We Are Marshal-appletv.mp4\n": "We Are Marshal.mp4"
    },
    "554": {
        "Wedding.Crashers[2005]DVDRip.AC3[Eng]-appletv.mp4\n": "Wedding Crashers[2005] [Eng].mp4"
    },
    "555": {
        "Weekend At Bernies 2-appletv.mp4\n": "Weekend At Bernies 2.mp4"
    },
    "556": {
        "Weekend At Bernies-appletv.mp4\n": "Weekend At Bernies.mp4"
    },
    "557": {
        "We're.the.Millers.2013.720p.BluRay.x264.YIFY-appletv3.mp4\n": "We're the Millers 2013 appletv3.mp4"
    },
    "558": {
        "What_A_Girl_Wants_(2003)-appletv.mp4\n": "What_A_Girl_Wants_(2003).mp4"
    },
    "559": {
        "White Chicks Unrated-appletv.mp4\n": "White Chicks Unrated.mp4"
    },
    "560": {
        "White.House.Down.2013.1080p.BluRay.x264.YIFY-appletv3.mp4\n": "White House Down 2013 appletv3.mp4"
    },
    "561": {
        "Who Framed Roger Rabbit [1988]-appletv.mp4\n": "Who Framed Roger Rabbit [1988].mp4"
    },
    "562": {
        "Without A Paddle.mp4\n": "Without A Paddle.mp4"
    },
    "563": {
        "World.War.Z.2013.1080p.BluRay.x264.YIFY-appletv3.mp4\n": "World War Z 2013 appletv3.mp4"
    },
    "564": {
        "[ www.UsaBit.com ] - Facing The Giants (2006) BluRay 720p 700MB Ganool-appletv3.mp4\n": "[ www UsaBit com ] Facing The Giants (2006) 700MB Ganoolappletv3.mp4"
    },
    "565": {
        "[www.UsaBit.com] - grace.unplugged.2013.bdrip.x264-sparks-ps3.mp4\n": "[www UsaBit com] grace unplugged 2013 x264sparksps3.mp4"
    },
    "566": {
        "X2[2003]DvDrip-aXXo-appletv.mp4\n": "X2[2003]DvDripaXXo.mp4"
    },
    "567": {
        "X-Men[2000]DvDrip-aXXo-appletv.mp4\n": "XMen[2000]DvDripaXXo.mp4"
    },
    "568": {
        "X-Men-The.Last.Stand[2006]DvDrip-aXXo-appletv.mp4\n": "XMenThe Last Stand[2006]DvDripaXXo.mp4"
    },
    "569": {
        "X-Men.X2.X-Men.United.BluRay.1080p.x264.5.1.Judas-appletv3.mp4\n": "XMen X2 XMen United 5 1 Judasappletv3.mp4"
    },
    "570": {
        "XXX-appletv.mp4\n": "XXX.mp4"
    },
    "571": {
        "Year One.2009.DvdRip.Unrated.Xvid {1337x}-Noir-appletv.mp4\n": "Year One 2009 Unrated {}Noir.mp4"
    },
    "572": {
        "Yes.Man.2008.DvDRip-FxM-appletv.mp4\n": "Yes Man 2008 DvDRipFxM.mp4"
    },
    "573": {
        "Zack and Miri Make A Porno-PARENTE-appletv.mp4\n": "Zack and Miri Make A PornoPARENTE.mp4"
    },
    "574": {
        "Zeitgeist Remastered Edition-appletv.mp4\n": "Zeitgeist Remastered Edition.mp4"
    },
    "575": {
        "Zombieland (2009) DVDRip XviD-MAX www.torentz.3xforum.ro-appletv.mp4\n": "Zombieland (2009) XviDMAX www torentz 3xforum ro.mp4"
    },
    "576": {
        "Zoolander-ETRG-appletv.mp4\n": "ZoolanderETRG.mp4"
    },
    "577": {
        "john.carter.2012.720p.bluray.x264-sparks.publichd-appletv.mp4\n": "john carter 2012 x264sparks.mp4"
    },
    "578": {
        "just.friends.720p-dimension.mkv\n": "just friends 720pdimension.mkv"
    },
    "579": {
        "killing.them.softly.2012.720p.bluray.dts.x264-publichd-appletv.mp4\n": "killing them softly 2012 dts x264publichd.mp4"
    },
    "580": {
        "Lente-appletv.m4v\n": "Lente.m4v"
    },
    "581": {
        "man.on.fire.2004-appletv.mp4\n": "man on fire 2004.mp4"
    },
    "582": {
        "m-cloudy-720p-appletv.mp4\n": "mcloudy720p.mp4"
    },
    "583": {
        "mission.impossible.ghost.protocol.2011.720p.bluray.x264-sparks  [PublicHD.ORG]-appletv.m4v\n": "mission impossible ghost protocol 2011 x264sparks [ ORG].m4v"
    },
    "584": {
        "paranorman.2012.720p.bluray.x264-sparks-appletv.mp4\n": "paranorman 2012 x264sparks.mp4"
    },
    "585": {
        "Planet Earth.m4v\n": "Planet Earth.m4v"
    },
    "586": {
        "Planet Earth pt. 2.m4v\n": "Planet Earth pt 2.m4v"
    },
    "587": {
        "Planet Earth pt 3.m4v\n": "Planet Earth pt 3.m4v"
    },
    "588": {
        "premium.rush.2012.720p.bluray.dts.x264-publichd-appletv.mp4\n": "premium rush 2012 dts x264publichd.mp4"
    },
    "589": {
        "refined-chronicle-720p-appletv.mp4\n": "refinedchronicle720p.mp4"
    },
    "590": {
        "refined-realsteel-720p-appletv.mp4\n": "refinedrealsteel720p.mp4"
    },
    "591": {
        "Safe House.mp4\n": "Safe House.mp4"
    },
    "592": {
        "Savages (2012).m4v\n": "Savages (2012).m4v"
    },
    "593": {
        "seeking.a.friend.for.the.end.of.the.world.2012.720p.bluray.x264-sparks-appletv.mp4\n": "seeking a friend for the end of the world 2012 x264sparks.mp4"
    },
    "594": {
        "Sherlock Holmes 2.mp4\n": "Sherlock Holmes 2.mp4"
    },
    "595": {
        "Shutter Island (2010).mp4\n": "Shutter Island (2010).mp4"
    },
    "596": {
        "Skyfall.mp4\n": "Skyfall.mp4"
    },
    "597": {
        "Spectre 2015 1080p BluRay x264 DTS-JYK.mkv\n": "Spectre 2015 .mkv"
    },
    "598": {
        "Step Up 3D 2010 720p.mp4\n": "Step Up 3D 2010.mp4"
    },
    "599": {
        "Step.Up.Revolution.2012.720p.Bluray.x264.YIFY.mp4\n": "Step Up Revolution 2012 .mp4"
    },
    "600": {
        "Taken 2 2012 720p BluRay x264 - Exclusive-appletv.m4v\n": "Taken 2 2012 Exclusive.m4v"
    },
    "601": {
        "Ted.2012.BluRay.720p.x264.YIFY.mp4\n": "Ted 2012 .mp4"
    },
    "602": {
        "Thank.You.For.Your.Service.2017.1080p.BRRip.6C.MkvCage.FardaDL.mkv\n": "Thank You For Your Service 2017 6C MkvCage FardaDL.mkv"
    },
    "603": {
        "The.Amazing.Spiderman.2012.1080p.BrRip.x264.YIFY.mp4\n": "The Amazing Spiderman 2012 .mp4"
    },
    "604": {
        "The.Amazing.Spider-Man.2.2014.1080p.BluRay.6CH.ShAaNiG.com.mkv\n": "The Amazing SpiderMan 2 2014 6CH ShAaNiG com.mkv"
    },
    "605": {
        "The.Avengers.2012.720p.BluRay.x264-NYDIC-appletv.mp4\n": "The Avengers 2012 x264NYDIC.mp4"
    },
    "606": {
        "The.Cabin.in.the.Woods.2012.KORSUB.720p.HDRip.x264.AC3-JYK-appletv.m4v\n": "The Cabin in the Woods 2012 KORSUB HDRip AC3JYK.m4v"
    },
    "607": {
        "the.campaign.2012.extended.720p.bluray.x264-sparks-appletv.mp4\n": "the campaign 2012 extended x264sparks.mp4"
    },
    "608": {
        "The.Dark.Knight.2008.1080p.x264.DTS-WAFHD-appletv.mp4\n": "The Dark Knight 2008 DTSWAFHD.mp4"
    },
    "609": {
        "the.dark.knight.rises.2012.720p.bluray.x264-sparks-appletv.mp4\n": "the dark knight rises 2012 x264sparks.mp4"
    },
    "610": {
        "The.Da.Vinci.Code.2006.1080p.BluRay.x264.anoXmous._-ps3.mp4\n": "The Da Vinci Code 2006 anoXmous _ps3.mp4"
    },
    "611": {
        "The.Dictator.2012.720p.BluRay.X264-AMIABLE-appletv.mp4\n": "The Dictator 2012 X264AMIABLE.mp4"
    },
    "612": {
        "The.Five.Year.Engagement.2012.UNRATED.720p.BluRay.X264.YIFY.mp4\n": "The Five Year Engagement 2012 UNRATED .mp4"
    },
    "613": {
        "The.Girl.With.The.Dragon.Tattoo.2011.720p.BluRay.x264.YIFY.mp4\n": "The Girl With The Dragon Tattoo 2011 .mp4"
    },
    "614": {
        "The HIt List 1080p-appletv.mp4\n": "The HIt List.mp4"
    },
    "615": {
        "The.Hunger.Games.1080p.BluRay.x264.YIFY.mp4\n": "The Hunger Games .mp4"
    },
    "616": {
        "The Lincoln Lawyer-appletv.m4v\n": "The Lincoln Lawyer.m4v"
    },
    "617": {
        "The Lion King Trilogy 720p BDRip [A Release-Lounge H264]\n": "The Lion King Trilogy [A ReleaseLounge H264]"
    },
    "618": {
        "The.Lorax.2012.720p.BluRay.x264-SiNNERS-appletv.mp4\n": "The Lorax 2012 x264SiNNERS.mp4"
    },
    "619": {
        "The.Lucky.One.2012.720p.BluRay.X264-AMIABLE-appletv.mp4\n": "The Lucky One 2012 X264AMIABLE.mp4"
    },
    "620": {
        "The.Man.with.the.Iron.Fists.2012.UNRATED.1080p.x264.YIFY.mp4\n": "The Man with the Iron Fists 2012 UNRATED .mp4"
    },
    "621": {
        "The Pianist {2002} - Mr. KickASS.mp4\n": "The Pianist {2002} Mr KickASS.mp4"
    },
    "622": {
        "The.Raid.Redemption.2011.720p.HDRip.DD5.1.Eng.NL.Subs-appletv.m4v\n": "The Raid Redemption 2011 HDRip DD5 1 Eng NL Subs.m4v"
    },
    "623": {
        "The Rum Diary 720p.mkv\n": "The Rum Diary.mkv"
    },
    "624": {
        "The.Scorpion.King.3.Battle.for.Redemption.2012.720p.Bluray.x264.DTS-HDChina-appletv.mp4\n": "The Scorpion King 3 Battle for Redemption 2012 DTSHDChina.mp4"
    },
    "625": {
        "The Social Network 720p-appletv.mp4\n": "The Social Network.mp4"
    },
    "626": {
        "The.Town.EXTENDED.2010.720p.BrRip.x264.YIFY.mp4\n": "The Town EXTENDED 2010 .mp4"
    },
    "627": {
        "The Twilight Saga Breaking Dawn-Part1[2011]BRRip XviD-ETRG-appletv.mp4\n": "The Twilight Saga Breaking DawnPart1[2011] XviDETRG.mp4"
    },
    "628": {
        "The Watch 2012 720p HDrip AC3-ViBE-appletv.m4v\n": "The Watch 2012 HDrip AC3ViBE.m4v"
    },
    "629": {
        "The.Wolf.of.Wall.Street.2013.720p.BluRay.X264-AMIABLE-ps3.mp4\n": "The Wolf of Wall Street 2013 X264AMIABLEps3.mp4"
    },
    "630": {
        "Think Like A Man 2012 720p BRRip x264 aac vice-quicktime.mov\n": "Think Like A Man 2012 vicequicktime.mov"
    },
    "631": {
        "this.means.war.2012.unrated.720p.bluray.x264-sparks-appletv.mp4\n": "this means war 2012 unrated x264sparks.mp4"
    },
    "632": {
        "Thor(2011)-appletv.mp4\n": "Thor(2011).mp4"
    },
    "633": {
        "Thor.Ragnarok.2017.1080p.BluRay.x264-[YTS.AG].mp4\n": "Thor Ragnarok 2017 [YTS AG].mp4"
    },
    "634": {
        "Three Kingdoms 720p.mp4\n": "Three Kingdoms.mp4"
    },
    "635": {
        "Tower.Heist.2011.720p.BluRay.X264-AMIABLE-appletv.mp4\n": "Tower Heist 2011 X264AMIABLE.mp4"
    },
    "636": {
        "Training Day 720p-appletv.m4v\n": "Training Day.m4v"
    },
    "637": {
        "Transformers.Age.of.Extinction.2014.1080p.WEB-DL.DD51.mp4\n": "Transformers Age of Extinction 2014 WEBDL DD51.mp4"
    },
    "638": {
        "Transformers Trilogy 2007 2009 2011Bluray 720p\n": "Transformers Trilogy 2007 2009 2011Bluray"
    },
    "639": {
        "Tron Legacy BluRay 720p-appletv.mp4\n": "Tron Legacy .mp4"
    },
    "640": {
        "Twilight Saga the Trilogy 720p h264\n": "Twilight Saga the Trilogy h264"
    },
    "641": {
        "UNDERWORLD 1-2-3 HD 720p BRRip 5.1AAC x264-ILPruny\n": "UNDERWORLD 123 HD 5.1AAC x264ILPruny"
    },
    "642": {
        "Underworld.Awakening.2012.720p.BluRay.x264-DON [PublicHD]-appletv.m4v\n": "Underworld Awakening 2012 x264DON [].m4v"
    },
    "643": {
        "Wall Street - Money Never Sleeps (HD).m4v\n": "Wall Street Money Never Sleeps (HD).m4v"
    },
    "644": {
        "Warcraft 2016 1080p WEB-DL x264 AC3-JYK.mkv\n": "Warcraft 2016 WEBDL AC3JYK.mkv"
    },
    "645": {
        "Warrior.2011.720p.BRRip.x264.AAC-ViSiON-quicktime.mov\n": "Warrior 2011 ViSiONquicktime.mov"
    },
    "646": {
        "What's Your Number UNRATED 2011 720p BRRip [A Release-Lounge H264].mp4\n": "What's Your Number UNRATED 2011 [A ReleaseLounge H264].mp4"
    },
    "647": {
        "Winter-appletv.m4v\n": "Winter.m4v"
    },
    "648": {
        "X-Men Apocalypse 2016 1080p BluRay x264 DTS-JYK.mkv\n": "XMen Apocalypse 2016 .mkv"
    },
    "649": {
        "X-Men-First Class [2011] 720p Blu-Ray x264 7.1 Ch AAC - ExtraTorrentRG-appletv.mp4\n": "XMenFirst Class [2011] 7 1 Ch .mp4"
    },
    "650": {
        "X-Men Origins Wolverine 2009 720p BRRip H.264 5.1 AC3-frapper(HDScene Release)-appletv.m4v\n": "XMen Origins Wolverine 2009 H 264 5 1 AC3frapper(HDScene Release).m4v"
    },
    "651": {
        "Zomer-appletv.m4v\n": "Zomer.m4v"
    }
}